{
	"Basic Scout" :
	{
		"class" : "scout",
		"weapons" : ["tf_weapon_scattergun"],
		"difficulty" : 3,
		"behavior" : "Mobber",
		"weapon_restriction" : "PrimaryOnly",
		"health" : "125+20*wave",
		"scale"	: 1.0,
		"max_vision_range" : 1200,
		"class_icon" : "scout",
		"auto_jump_min" : 0,
		"auto_jump_max"	: 0,
		
		"attributes" : [ ["damage bonus","1.0+0.3*wave"] ]
	},
	"Basic Soldier" :
	{
		"class" : "soldier",
		"weapons" : ["tf_weapon_rocketlauncher"],
		"difficulty" : 3,
		"behavior" : "Mobber",
		"weapon_restriction" : "PrimaryOnly",
		"health" : "200+35*wave",
		"attributes" : [ ["damage bonus","1.0+0.3*wave"] ]
	},
	"Basic Pyro" :
	{
		"class" : "pyro",
		"weapons" : ["tf_weapon_flamethrower"],
		"difficulty" : 3,
		"behavior" : "Mobber",
		"weapon_restriction" : "PrimaryOnly",
		"health" : "175+30*wave",
		"attributes" : [ ["damage bonus","1.0+0.3*wave"] ]
	},
	"Basic Demoman" :
	{
		"class" : "demoman",
		"weapons" : ["tf_weapon_grenadelauncher"],
		"difficulty" : 3,
		"behavior" : "Mobber",
		"weapon_restriction" : "PrimaryOnly",
		"health" : "175+30*wave",
		"attributes" : [ ["damage bonus","1.0+0.3*wave"] ]
	},
	"Basic Heavy" :
	{
		"class" : "heavy",
		"weapons" : ["tf_weapon_minigun"],
		"difficulty" : 3,
		"behavior" : "Mobber",
		"weapon_restriction" : "PrimaryOnly",
		"health" : "300+50*wave",
		"attributes" : [ ["damage bonus","1.0+0.3*wave"] ]
	},
	"Basic Engineer" :
	{
		"class" : "engineer",
		"weapons" : ["tf_weapon_shotgun_primary", "tf_weapon_pistol", "tf_weapon_wrench"],
		"difficulty" : 3,
		"health" : "300+20*wave",
		"attributes" : [ ["damage bonus","1.0+0.3*wave"] ]
	},
	"Basic Medic" :
	{
		"class" : "medic",
		"weapons" : ["Crusader's Crossbow", "tf_weapon_medigun", "tf_weapon_bonesaw"],
		"difficulty" : 3,
		"health" : "150+20*wave",
		"attributes" : [ ["damage bonus","1.0+0.3*wave"] ]
	},
	"Basic Sniper" :
	{
		"class" : "sniper",
		"weapons" : ["tf_weapon_sniperrifle"],
		"weapon_restriction" : "PrimaryOnly",
		"difficulty" : 3,
		"health" : "125+20*wave",
		"attributes" : [ ["damage bonus","1.0+0.3*wave"] ]
	},
	"Basic Spy" :
	{
		"class" : "spy",
		"weapons" : ["tf_weapon_revolver", "tf_weapon_knife"],
		"difficulty" : 3,
		"health" : "125+20*wave",
		"attributes" : [ ["damage bonus","1.0+0.3*wave"] ]
	},
	"Blunt Launcher" :
	{
		"class" : "soldier",
		"weapons" : ["The Original", "The Battalion's Backup", "The Disciplinary Action"],
		"difficulty" : 3,
		"behavior" : "Push",
		"weapon_restriction" : "PrimaryOnly",
		"bot_attributes" : ["AlwaysCrits", "MiniBoss", "UseBossHealthBar"],
		"tags" : ["bot_giant", "bot_gatebot"],
		"health" : "5000+2000*wave",
		"is_boss" : true,
		"scale"	: 1.7,
		"max_vision_range" : 2500,
		"class_icon" : "soldier_barrage",
		"auto_jump_min" : 0,
		"auto_jump_max"	: 0,
		"attributes" : [ ["damage bonus","1.0+0.3*wave"], ["fire rate bonus","0.2 * 0.9^wave"], ["faster reload rate","0.1 * 0.9^wave"],
		["clip size bonus","2.0 * 1.2^wave"], ["projectile spread angle penalty","4.0"], ["move speed penalty","0.5"], ["override footstep sound set","3"]
		, ["dmg taken increased","0.95^wave"] ]
	}
}